{"es_guide_routing.md":"b845398a","es_guide_theme-badge.md":"c2f1932c","es_guide_theme-carbon-ads.md":"6d791e3b","es_guide_theme-introduction.md":"7991c26d","es_guide_theme-last-updated.md":"80344fb8","es_guide_theme-layout.md":"b1dd4b0d","es_guide_theme-nav.md":"aecc611e","es_guide_theme-prev-next-link.md":"596a6fcc","es_guide_theme-search.md":"9edfad18","es_guide_theme-sidebar.md":"2bf5b079","es_guide_theme-team-page.md":"3add2c84","es_guide_using-vue.md":"9f985e3c","es_guide_what-is-vitepress.md":"2ac11dae","es_index.md":"67f5b265","guide_api.md":"21ef82b2","guide_asset-handling.md":"c70e515a","it_guide_theme-sidebar.md":"34823735","guide_configuration.md":"75569dce","it_guide_getting-started.md":"37543c64","guide_deploying.md":"bd2ca154","guide_frontmatter.md":"b31e00eb","guide_getting-started.md":"7b64734a","guide_i18n.md":"eabcd520","guide_markdown.md":"0d35239b","guide_migration-from-vitepress-0.md":"75fe2925","guide_migration-from-vuepress.md":"3cd1e987","guide_routing.md":"5fe80994","guide_theme-badge.md":"28c16441","guide_theme-carbon-ads.md":"8a109a33","guide_theme-edit-link.md":"f67f6f16","guide_theme-footer.md":"8b48727b","guide_theme-home-page.md":"0efe6d14","guide_theme-introduction.md":"d9d43996","guide_theme-last-updated.md":"65e2c1e4","guide_theme-layout.md":"dec874d6","guide_theme-nav.md":"7cc6c671","guide_theme-prev-next-link.md":"0f3adfff","guide_theme-search.md":"66d5dacd","guide_theme-sidebar.md":"846b3a5d","guide_theme-team-page.md":"51eb7d80","guide_using-vue.md":"88462f7a","guide_what-is-vitepress.md":"1bec33bb","index.md":"d209170c","it_config_app-configs.md":"315224b8","it_config_frontmatter-configs.md":"3bed976f","it_config_introduction.md":"8d55c553","it_config_theme-configs.md":"1e793788","it_guide_api.md":"1b3f3afa","it_guide_asset-handling.md":"875d1321","it_guide_configuration.md":"f880a3f5","it_guide_frontmatter.md":"230eaf3b","it_guide_i18n.md":"be9f706d","it_guide_markdown.md":"c6c7a362","it_guide_migration-from-vitepress-0.md":"d0ddcb67","it_guide_migration-from-vuepress.md":"dbac735a","it_guide_routing.md":"4c98abf7","it_guide_theme-badge.md":"c012c857","it_guide_theme-carbon-ads.md":"780e4672","it_guide_theme-edit-link.md":"526941c4","it_guide_theme-footer.md":"ea9db21e","it_guide_theme-home-page.md":"8e354c82","it_guide_theme-introduction.md":"ef55c1e2","it_guide_theme-last-updated.md":"bfaa5c9f","it_guide_theme-layout.md":"8d0881fe","it_guide_theme-nav.md":"1ffc4fa2","it_guide_deploying.md":"d7ac9215","it_guide_theme-prev-next-link.md":"034e27a3","it_guide_theme-team-page.md":"d98f8d05","it_guide_using-vue.md":"324355cd","it_guide_what-is-vitepress.md":"e9708712","it_index.md":"02783fb1","config_app-configs.md":"12b0f85c","config_frontmatter-configs.md":"79e9bdd4","es_guide_asset-handling.md":"04ebe19a","config_introduction.md":"740b7b28","config_theme-configs.md":"e863b1c1","es_config_app-configs.md":"d6076404","es_config_frontmatter-configs.md":"b7f988bd","es_guide_configuration.md":"c0a198d1","es_config_introduction.md":"e186f07e","es_guide_deploying.md":"28764a91","es_guide_frontmatter.md":"5f062103","es_config_theme-configs.md":"ec1020c8","es_guide_theme-edit-link.md":"69501b40","es_guide_api.md":"8c3e040b","es_guide_i18n.md":"079dedbc","es_guide_markdown.md":"43d1c226","es_guide_migration-from-vitepress-0.md":"4bf051d1","es_guide_migration-from-vuepress.md":"f4bd6564","es_guide_getting-started.md":"078255d7","es_guide_theme-footer.md":"b9b44573","es_guide_theme-home-page.md":"7e8620e8","it_guide_theme-search.md":"9acd3f69"}
